pyagify/__init__.py
pyagify/agify.py
pyagify/exceptions.py
py_agify-0.0.1.dist-info/LICENSE
py_agify-0.0.1.dist-info/METADATA
py_agify-0.0.1.dist-info/WHEEL
py_agify-0.0.1.dist-info/top_level.txt
py_agify-0.0.1.dist-info/RECORD
